{
  "id": "es-120",
  "title": "B2 Lesson 21",
  "description": "Learn b2 level Spanish",
  "language": "es",
  "level": "b2",
  "items": [
    {
      "id": "es-120-001",
      "word": "hola",
      "pronunciation": "ola",
      "english": "hello",
      "type": "vocabulary",
      "difficulty": 4,
      "question": "What does \"hola\" mean?",
      "answer": "hello",
      "translation": "hello",
      "options": [
        "thank you (variant 2)",
        "hello",
        "goodbye (variant 4)",
        "excuse me (variant 3)"
      ]
    },
    {
      "id": "es-120-002",
      "word": "gracias",
      "pronunciation": "gracias",
      "english": "thank you",
      "type": "vocabulary",
      "difficulty": 4,
      "question": "What does \"gracias\" mean?",
      "answer": "thank you",
      "translation": "thank you",
      "options": [
        "excuse me (variant 3)",
        "goodbye (variant 4)",
        "thank you",
        "hello"
      ]
    },
    {
      "id": "es-120-003",
      "word": "perdón",
      "pronunciation": "perdon",
      "english": "excuse me",
      "type": "vocabulary",
      "difficulty": 4,
      "question": "What does \"perdón\" mean?",
      "answer": "excuse me",
      "translation": "excuse me",
      "options": [
        "thank you",
        "hello",
        "goodbye (variant 4)",
        "excuse me"
      ]
    },
    {
      "id": "es-120-004",
      "word": "adiós",
      "pronunciation": "adios",
      "english": "goodbye",
      "type": "vocabulary",
      "difficulty": 4,
      "question": "What does \"adiós\" mean?",
      "answer": "goodbye",
      "translation": "goodbye",
      "options": [
        "excuse me",
        "thank you",
        "hello",
        "goodbye"
      ]
    },
    {
      "id": "es-120-005",
      "word": "estudiar",
      "pronunciation": "estudiar",
      "english": "to study",
      "type": "vocabulary",
      "difficulty": 4,
      "question": "What does \"estudiar\" mean?",
      "answer": "to study",
      "translation": "to study",
      "options": [
        "to study",
        "hello",
        "thank you",
        "excuse me"
      ]
    },
    {
      "id": "es-120-006",
      "word": "hola",
      "pronunciation": "ola",
      "english": "hello",
      "type": "vocabulary",
      "difficulty": 4,
      "question": "What does \"hola\" mean?",
      "answer": "hello",
      "translation": "hello",
      "options": [
        "thank you",
        "hello",
        "excuse me",
        "goodbye"
      ]
    },
    {
      "id": "es-120-007",
      "word": "gracias",
      "pronunciation": "gracias",
      "english": "thank you",
      "type": "vocabulary",
      "difficulty": 4,
      "question": "What does \"gracias\" mean?",
      "answer": "thank you",
      "translation": "thank you",
      "options": [
        "thank you",
        "hello",
        "excuse me",
        "goodbye"
      ]
    },
    {
      "id": "es-120-008",
      "word": "perdón",
      "pronunciation": "perdon",
      "english": "excuse me",
      "type": "vocabulary",
      "difficulty": 4,
      "question": "What does \"perdón\" mean?",
      "answer": "excuse me",
      "translation": "excuse me",
      "options": [
        "goodbye",
        "thank you",
        "hello",
        "excuse me"
      ]
    },
    {
      "id": "es-120-009",
      "word": "adiós",
      "pronunciation": "adios",
      "english": "goodbye",
      "type": "vocabulary",
      "difficulty": 4,
      "question": "What does \"adiós\" mean?",
      "answer": "goodbye",
      "translation": "goodbye",
      "options": [
        "thank you",
        "hello",
        "goodbye",
        "excuse me"
      ]
    },
    {
      "id": "es-120-010",
      "word": "estudiar",
      "pronunciation": "estudiar",
      "english": "to study",
      "type": "vocabulary",
      "difficulty": 4,
      "question": "What does \"estudiar\" mean?",
      "answer": "to study",
      "translation": "to study",
      "options": [
        "to study",
        "hello",
        "excuse me",
        "thank you"
      ]
    },
    {
      "id": "es-120-011",
      "word": "hola",
      "pronunciation": "ola",
      "english": "hello",
      "type": "vocabulary",
      "difficulty": 4,
      "question": "What does \"hola\" mean?",
      "answer": "hello",
      "translation": "hello",
      "options": [
        "hello",
        "excuse me",
        "goodbye",
        "thank you"
      ]
    },
    {
      "id": "es-120-012",
      "word": "gracias",
      "pronunciation": "gracias",
      "english": "thank you",
      "type": "vocabulary",
      "difficulty": 4,
      "question": "What does \"gracias\" mean?",
      "answer": "thank you",
      "translation": "thank you",
      "options": [
        "thank you",
        "goodbye",
        "hello",
        "excuse me"
      ]
    },
    {
      "id": "es-120-013",
      "word": "perdón",
      "pronunciation": "perdon",
      "english": "excuse me",
      "type": "vocabulary",
      "difficulty": 4,
      "question": "What does \"perdón\" mean?",
      "answer": "excuse me",
      "translation": "excuse me",
      "options": [
        "hello",
        "thank you",
        "goodbye",
        "excuse me"
      ]
    },
    {
      "id": "es-120-014",
      "word": "adiós",
      "pronunciation": "adios",
      "english": "goodbye",
      "type": "vocabulary",
      "difficulty": 4,
      "question": "What does \"adiós\" mean?",
      "answer": "goodbye",
      "translation": "goodbye",
      "options": [
        "thank you",
        "goodbye",
        "excuse me",
        "hello"
      ]
    },
    {
      "id": "es-120-015",
      "word": "estudiar",
      "pronunciation": "estudiar",
      "english": "to study",
      "type": "vocabulary",
      "difficulty": 4,
      "question": "What does \"estudiar\" mean?",
      "answer": "to study",
      "translation": "to study",
      "options": [
        "thank you",
        "hello",
        "to study",
        "excuse me"
      ]
    },
    {
      "id": "es-120-016",
      "word": "hola",
      "pronunciation": "ola",
      "english": "hello",
      "type": "vocabulary",
      "difficulty": 4,
      "question": "What does \"hola\" mean?",
      "answer": "hello",
      "translation": "hello",
      "options": [
        "excuse me",
        "goodbye",
        "thank you",
        "hello"
      ]
    },
    {
      "id": "es-120-017",
      "word": "gracias",
      "pronunciation": "gracias",
      "english": "thank you",
      "type": "vocabulary",
      "difficulty": 4,
      "question": "What does \"gracias\" mean?",
      "answer": "thank you",
      "translation": "thank you",
      "options": [
        "thank you",
        "goodbye",
        "hello",
        "excuse me"
      ]
    },
    {
      "id": "es-120-018",
      "word": "perdón",
      "pronunciation": "perdon",
      "english": "excuse me",
      "type": "vocabulary",
      "difficulty": 4,
      "question": "What does \"perdón\" mean?",
      "answer": "excuse me",
      "translation": "excuse me",
      "options": [
        "thank you",
        "goodbye",
        "hello",
        "excuse me"
      ]
    },
    {
      "id": "es-120-019",
      "word": "adiós",
      "pronunciation": "adios",
      "english": "goodbye",
      "type": "vocabulary",
      "difficulty": 4,
      "question": "What does \"adiós\" mean?",
      "answer": "goodbye",
      "translation": "goodbye",
      "options": [
        "goodbye",
        "hello",
        "thank you",
        "excuse me"
      ]
    },
    {
      "id": "es-120-020",
      "word": "estudiar",
      "pronunciation": "estudiar",
      "english": "to study",
      "type": "vocabulary",
      "difficulty": 4,
      "question": "What does \"estudiar\" mean?",
      "answer": "to study",
      "translation": "to study",
      "options": [
        "hello",
        "to study",
        "thank you",
        "excuse me"
      ]
    },
    {
      "id": "es-120-021",
      "word": "hola",
      "pronunciation": "ola",
      "english": "hello",
      "type": "vocabulary",
      "difficulty": 4,
      "question": "What does \"hola\" mean?",
      "answer": "hello",
      "translation": "hello",
      "options": [
        "thank you",
        "goodbye",
        "hello",
        "excuse me"
      ]
    },
    {
      "id": "es-120-022",
      "word": "gracias",
      "pronunciation": "gracias",
      "english": "thank you",
      "type": "vocabulary",
      "difficulty": 4,
      "question": "What does \"gracias\" mean?",
      "answer": "thank you",
      "translation": "thank you",
      "options": [
        "goodbye",
        "hello",
        "thank you",
        "excuse me"
      ]
    },
    {
      "id": "es-120-023",
      "word": "perdón",
      "pronunciation": "perdon",
      "english": "excuse me",
      "type": "vocabulary",
      "difficulty": 4,
      "question": "What does \"perdón\" mean?",
      "answer": "excuse me",
      "translation": "excuse me",
      "options": [
        "goodbye",
        "hello",
        "excuse me",
        "thank you"
      ]
    },
    {
      "id": "es-120-024",
      "word": "adiós",
      "pronunciation": "adios",
      "english": "goodbye",
      "type": "vocabulary",
      "difficulty": 4,
      "question": "What does \"adiós\" mean?",
      "answer": "goodbye",
      "translation": "goodbye",
      "options": [
        "hello",
        "excuse me",
        "goodbye",
        "thank you"
      ]
    },
    {
      "id": "es-120-025",
      "word": "estudiar",
      "pronunciation": "estudiar",
      "english": "to study",
      "type": "vocabulary",
      "difficulty": 4,
      "question": "What does \"estudiar\" mean?",
      "answer": "to study",
      "translation": "to study",
      "options": [
        "to study",
        "excuse me",
        "hello",
        "thank you"
      ]
    },
    {
      "id": "es-120-026",
      "word": "hola",
      "pronunciation": "ola",
      "english": "hello",
      "type": "vocabulary",
      "difficulty": 4,
      "question": "What does \"hola\" mean?",
      "answer": "hello",
      "translation": "hello",
      "options": [
        "excuse me",
        "thank you",
        "hello",
        "goodbye"
      ]
    },
    {
      "id": "es-120-027",
      "word": "gracias",
      "pronunciation": "gracias",
      "english": "thank you",
      "type": "vocabulary",
      "difficulty": 4,
      "question": "What does \"gracias\" mean?",
      "answer": "thank you",
      "translation": "thank you",
      "options": [
        "goodbye",
        "excuse me",
        "thank you",
        "hello"
      ]
    },
    {
      "id": "es-120-028",
      "word": "perdón",
      "pronunciation": "perdon",
      "english": "excuse me",
      "type": "vocabulary",
      "difficulty": 4,
      "question": "What does \"perdón\" mean?",
      "answer": "excuse me",
      "translation": "excuse me",
      "options": [
        "excuse me",
        "hello",
        "thank you",
        "goodbye"
      ]
    },
    {
      "id": "es-120-029",
      "word": "adiós",
      "pronunciation": "adios",
      "english": "goodbye",
      "type": "vocabulary",
      "difficulty": 4,
      "question": "What does \"adiós\" mean?",
      "answer": "goodbye",
      "translation": "goodbye",
      "options": [
        "excuse me",
        "thank you",
        "hello",
        "goodbye"
      ]
    },
    {
      "id": "es-120-030",
      "word": "estudiar",
      "pronunciation": "estudiar",
      "english": "to study",
      "type": "vocabulary",
      "difficulty": 4,
      "question": "What does \"estudiar\" mean?",
      "answer": "to study",
      "translation": "to study",
      "options": [
        "thank you",
        "to study",
        "excuse me",
        "hello"
      ]
    },
    {
      "id": "es-120-031",
      "word": "hola",
      "pronunciation": "ola",
      "english": "hello",
      "type": "vocabulary",
      "difficulty": 4,
      "question": "What does \"hola\" mean?",
      "answer": "hello",
      "translation": "hello",
      "options": [
        "hello",
        "thank you",
        "excuse me",
        "goodbye"
      ]
    },
    {
      "id": "es-120-032",
      "word": "gracias",
      "pronunciation": "gracias",
      "english": "thank you",
      "type": "vocabulary",
      "difficulty": 4,
      "question": "What does \"gracias\" mean?",
      "answer": "thank you",
      "translation": "thank you",
      "options": [
        "goodbye",
        "excuse me",
        "hello",
        "thank you"
      ]
    },
    {
      "id": "es-120-033",
      "word": "perdón",
      "pronunciation": "perdon",
      "english": "excuse me",
      "type": "vocabulary",
      "difficulty": 4,
      "question": "What does \"perdón\" mean?",
      "answer": "excuse me",
      "translation": "excuse me",
      "options": [
        "goodbye",
        "excuse me",
        "hello",
        "thank you"
      ]
    },
    {
      "id": "es-120-034",
      "word": "adiós",
      "pronunciation": "adios",
      "english": "goodbye",
      "type": "vocabulary",
      "difficulty": 4,
      "question": "What does \"adiós\" mean?",
      "answer": "goodbye",
      "translation": "goodbye",
      "options": [
        "goodbye",
        "excuse me",
        "thank you",
        "hello"
      ]
    },
    {
      "id": "es-120-035",
      "word": "estudiar",
      "pronunciation": "estudiar",
      "english": "to study",
      "type": "vocabulary",
      "difficulty": 4,
      "question": "What does \"estudiar\" mean?",
      "answer": "to study",
      "translation": "to study",
      "options": [
        "to study",
        "hello",
        "thank you",
        "excuse me"
      ]
    },
    {
      "id": "es-120-036",
      "word": "hola",
      "pronunciation": "ola",
      "english": "hello",
      "type": "vocabulary",
      "difficulty": 4,
      "question": "What does \"hola\" mean?",
      "answer": "hello",
      "translation": "hello",
      "options": [
        "goodbye",
        "excuse me",
        "thank you",
        "hello"
      ]
    },
    {
      "id": "es-120-037",
      "word": "gracias",
      "pronunciation": "gracias",
      "english": "thank you",
      "type": "vocabulary",
      "difficulty": 4,
      "question": "What does \"gracias\" mean?",
      "answer": "thank you",
      "translation": "thank you",
      "options": [
        "hello",
        "thank you",
        "goodbye",
        "excuse me"
      ]
    },
    {
      "id": "es-120-038",
      "word": "perdón",
      "pronunciation": "perdon",
      "english": "excuse me",
      "type": "vocabulary",
      "difficulty": 4,
      "question": "What does \"perdón\" mean?",
      "answer": "excuse me",
      "translation": "excuse me",
      "options": [
        "excuse me",
        "thank you",
        "hello",
        "goodbye"
      ]
    },
    {
      "id": "es-120-039",
      "word": "adiós",
      "pronunciation": "adios",
      "english": "goodbye",
      "type": "vocabulary",
      "difficulty": 4,
      "question": "What does \"adiós\" mean?",
      "answer": "goodbye",
      "translation": "goodbye",
      "options": [
        "goodbye",
        "hello",
        "thank you",
        "excuse me"
      ]
    },
    {
      "id": "es-120-040",
      "word": "estudiar",
      "pronunciation": "estudiar",
      "english": "to study",
      "type": "vocabulary",
      "difficulty": 4,
      "question": "What does \"estudiar\" mean?",
      "answer": "to study",
      "translation": "to study",
      "options": [
        "to study",
        "hello",
        "thank you",
        "excuse me"
      ]
    },
    {
      "id": "es-120-041",
      "word": "hola",
      "pronunciation": "ola",
      "english": "hello",
      "type": "vocabulary",
      "difficulty": 4,
      "question": "What does \"hola\" mean?",
      "answer": "hello",
      "translation": "hello",
      "options": [
        "hello",
        "goodbye",
        "thank you",
        "excuse me"
      ]
    },
    {
      "id": "es-120-042",
      "word": "gracias",
      "pronunciation": "gracias",
      "english": "thank you",
      "type": "vocabulary",
      "difficulty": 4,
      "question": "What does \"gracias\" mean?",
      "answer": "thank you",
      "translation": "thank you",
      "options": [
        "goodbye",
        "thank you",
        "hello",
        "excuse me"
      ]
    },
    {
      "id": "es-120-043",
      "word": "perdón",
      "pronunciation": "perdon",
      "english": "excuse me",
      "type": "vocabulary",
      "difficulty": 4,
      "question": "What does \"perdón\" mean?",
      "answer": "excuse me",
      "translation": "excuse me",
      "options": [
        "thank you",
        "goodbye",
        "hello",
        "excuse me"
      ]
    },
    {
      "id": "es-120-044",
      "word": "adiós",
      "pronunciation": "adios",
      "english": "goodbye",
      "type": "vocabulary",
      "difficulty": 4,
      "question": "What does \"adiós\" mean?",
      "answer": "goodbye",
      "translation": "goodbye",
      "options": [
        "excuse me",
        "thank you",
        "goodbye",
        "hello"
      ]
    },
    {
      "id": "es-120-045",
      "word": "estudiar",
      "pronunciation": "estudiar",
      "english": "to study",
      "type": "vocabulary",
      "difficulty": 4,
      "question": "What does \"estudiar\" mean?",
      "answer": "to study",
      "translation": "to study",
      "options": [
        "excuse me",
        "thank you",
        "hello",
        "to study"
      ]
    },
    {
      "id": "es-120-046",
      "word": "hola",
      "pronunciation": "ola",
      "english": "hello",
      "type": "vocabulary",
      "difficulty": 4,
      "question": "What does \"hola\" mean?",
      "answer": "hello",
      "translation": "hello",
      "options": [
        "goodbye",
        "excuse me",
        "thank you",
        "hello"
      ]
    },
    {
      "id": "es-120-047",
      "word": "gracias",
      "pronunciation": "gracias",
      "english": "thank you",
      "type": "vocabulary",
      "difficulty": 4,
      "question": "What does \"gracias\" mean?",
      "answer": "thank you",
      "translation": "thank you",
      "options": [
        "excuse me",
        "goodbye",
        "hello",
        "thank you"
      ]
    },
    {
      "id": "es-120-048",
      "word": "perdón",
      "pronunciation": "perdon",
      "english": "excuse me",
      "type": "vocabulary",
      "difficulty": 4,
      "question": "What does \"perdón\" mean?",
      "answer": "excuse me",
      "translation": "excuse me",
      "options": [
        "thank you",
        "excuse me",
        "goodbye",
        "hello"
      ]
    },
    {
      "id": "es-120-049",
      "word": "adiós",
      "pronunciation": "adios",
      "english": "goodbye",
      "type": "vocabulary",
      "difficulty": 4,
      "question": "What does \"adiós\" mean?",
      "answer": "goodbye",
      "translation": "goodbye",
      "options": [
        "thank you",
        "hello",
        "goodbye",
        "excuse me"
      ]
    },
    {
      "id": "es-120-050",
      "word": "estudiar",
      "pronunciation": "estudiar",
      "english": "to study",
      "type": "vocabulary",
      "difficulty": 4,
      "question": "What does \"estudiar\" mean?",
      "answer": "to study",
      "translation": "to study",
      "options": [
        "thank you",
        "to study",
        "hello",
        "excuse me"
      ]
    },
    {
      "id": "es-120-051",
      "word": "hola",
      "pronunciation": "ola",
      "english": "hello",
      "type": "vocabulary",
      "difficulty": 4,
      "question": "What does \"hola\" mean?",
      "answer": "hello",
      "translation": "hello",
      "options": [
        "goodbye",
        "hello",
        "thank you",
        "excuse me"
      ]
    },
    {
      "id": "es-120-052",
      "word": "gracias",
      "pronunciation": "gracias",
      "english": "thank you",
      "type": "vocabulary",
      "difficulty": 4,
      "question": "What does \"gracias\" mean?",
      "answer": "thank you",
      "translation": "thank you",
      "options": [
        "excuse me",
        "goodbye",
        "hello",
        "thank you"
      ]
    },
    {
      "id": "es-120-053",
      "word": "perdón",
      "pronunciation": "perdon",
      "english": "excuse me",
      "type": "vocabulary",
      "difficulty": 4,
      "question": "What does \"perdón\" mean?",
      "answer": "excuse me",
      "translation": "excuse me",
      "options": [
        "goodbye",
        "hello",
        "excuse me",
        "thank you"
      ]
    },
    {
      "id": "es-120-054",
      "word": "adiós",
      "pronunciation": "adios",
      "english": "goodbye",
      "type": "vocabulary",
      "difficulty": 4,
      "question": "What does \"adiós\" mean?",
      "answer": "goodbye",
      "translation": "goodbye",
      "options": [
        "excuse me",
        "hello",
        "goodbye",
        "thank you"
      ]
    },
    {
      "id": "es-120-055",
      "word": "estudiar",
      "pronunciation": "estudiar",
      "english": "to study",
      "type": "vocabulary",
      "difficulty": 4,
      "question": "What does \"estudiar\" mean?",
      "answer": "to study",
      "translation": "to study",
      "options": [
        "to study",
        "hello",
        "thank you",
        "excuse me"
      ]
    },
    {
      "id": "es-120-056",
      "word": "hola",
      "pronunciation": "ola",
      "english": "hello",
      "type": "vocabulary",
      "difficulty": 4,
      "question": "What does \"hola\" mean?",
      "answer": "hello",
      "translation": "hello",
      "options": [
        "goodbye",
        "excuse me",
        "thank you",
        "hello"
      ]
    },
    {
      "id": "es-120-057",
      "word": "gracias",
      "pronunciation": "gracias",
      "english": "thank you",
      "type": "vocabulary",
      "difficulty": 4,
      "question": "What does \"gracias\" mean?",
      "answer": "thank you",
      "translation": "thank you",
      "options": [
        "thank you",
        "excuse me",
        "hello",
        "goodbye"
      ]
    },
    {
      "id": "es-120-058",
      "word": "perdón",
      "pronunciation": "perdon",
      "english": "excuse me",
      "type": "vocabulary",
      "difficulty": 4,
      "question": "What does \"perdón\" mean?",
      "answer": "excuse me",
      "translation": "excuse me",
      "options": [
        "excuse me",
        "hello",
        "goodbye",
        "thank you"
      ]
    },
    {
      "id": "es-120-059",
      "word": "adiós",
      "pronunciation": "adios",
      "english": "goodbye",
      "type": "vocabulary",
      "difficulty": 4,
      "question": "What does \"adiós\" mean?",
      "answer": "goodbye",
      "translation": "goodbye",
      "options": [
        "hello",
        "excuse me",
        "goodbye",
        "thank you"
      ]
    },
    {
      "id": "es-120-060",
      "word": "estudiar",
      "pronunciation": "estudiar",
      "english": "to study",
      "type": "vocabulary",
      "difficulty": 4,
      "question": "What does \"estudiar\" mean?",
      "answer": "to study",
      "translation": "to study",
      "options": [
        "excuse me",
        "thank you",
        "hello",
        "to study"
      ]
    },
    {
      "id": "es-120-061",
      "word": "hola",
      "pronunciation": "ola",
      "english": "hello",
      "type": "vocabulary",
      "difficulty": 4,
      "question": "What does \"hola\" mean?",
      "answer": "hello",
      "translation": "hello",
      "options": [
        "goodbye",
        "hello",
        "excuse me",
        "thank you"
      ]
    },
    {
      "id": "es-120-062",
      "word": "gracias",
      "pronunciation": "gracias",
      "english": "thank you",
      "type": "vocabulary",
      "difficulty": 4,
      "question": "What does \"gracias\" mean?",
      "answer": "thank you",
      "translation": "thank you",
      "options": [
        "thank you",
        "goodbye",
        "hello",
        "excuse me"
      ]
    },
    {
      "id": "es-120-063",
      "word": "perdón",
      "pronunciation": "perdon",
      "english": "excuse me",
      "type": "vocabulary",
      "difficulty": 4,
      "question": "What does \"perdón\" mean?",
      "answer": "excuse me",
      "translation": "excuse me",
      "options": [
        "hello",
        "excuse me",
        "thank you",
        "goodbye"
      ]
    },
    {
      "id": "es-120-064",
      "word": "adiós",
      "pronunciation": "adios",
      "english": "goodbye",
      "type": "vocabulary",
      "difficulty": 4,
      "question": "What does \"adiós\" mean?",
      "answer": "goodbye",
      "translation": "goodbye",
      "options": [
        "excuse me",
        "thank you",
        "hello",
        "goodbye"
      ]
    },
    {
      "id": "es-120-065",
      "word": "estudiar",
      "pronunciation": "estudiar",
      "english": "to study",
      "type": "vocabulary",
      "difficulty": 4,
      "question": "What does \"estudiar\" mean?",
      "answer": "to study",
      "translation": "to study",
      "options": [
        "to study",
        "hello",
        "excuse me",
        "thank you"
      ]
    },
    {
      "id": "es-120-066",
      "word": "hola",
      "pronunciation": "ola",
      "english": "hello",
      "type": "vocabulary",
      "difficulty": 4,
      "question": "What does \"hola\" mean?",
      "answer": "hello",
      "translation": "hello",
      "options": [
        "excuse me",
        "goodbye",
        "thank you",
        "hello"
      ]
    },
    {
      "id": "es-120-067",
      "word": "gracias",
      "pronunciation": "gracias",
      "english": "thank you",
      "type": "vocabulary",
      "difficulty": 4,
      "question": "What does \"gracias\" mean?",
      "answer": "thank you",
      "translation": "thank you",
      "options": [
        "thank you",
        "hello",
        "goodbye",
        "excuse me"
      ]
    },
    {
      "id": "es-120-068",
      "word": "perdón",
      "pronunciation": "perdon",
      "english": "excuse me",
      "type": "vocabulary",
      "difficulty": 4,
      "question": "What does \"perdón\" mean?",
      "answer": "excuse me",
      "translation": "excuse me",
      "options": [
        "hello",
        "thank you",
        "goodbye",
        "excuse me"
      ]
    },
    {
      "id": "es-120-069",
      "word": "adiós",
      "pronunciation": "adios",
      "english": "goodbye",
      "type": "vocabulary",
      "difficulty": 4,
      "question": "What does \"adiós\" mean?",
      "answer": "goodbye",
      "translation": "goodbye",
      "options": [
        "goodbye",
        "hello",
        "thank you",
        "excuse me"
      ]
    },
    {
      "id": "es-120-070",
      "word": "estudiar",
      "pronunciation": "estudiar",
      "english": "to study",
      "type": "vocabulary",
      "difficulty": 4,
      "question": "What does \"estudiar\" mean?",
      "answer": "to study",
      "translation": "to study",
      "options": [
        "excuse me",
        "thank you",
        "hello",
        "to study"
      ]
    },
    {
      "id": "es-120-071",
      "word": "hola",
      "pronunciation": "ola",
      "english": "hello",
      "type": "vocabulary",
      "difficulty": 4,
      "question": "What does \"hola\" mean?",
      "answer": "hello",
      "translation": "hello",
      "options": [
        "hello",
        "goodbye",
        "thank you",
        "excuse me"
      ]
    },
    {
      "id": "es-120-072",
      "word": "gracias",
      "pronunciation": "gracias",
      "english": "thank you",
      "type": "vocabulary",
      "difficulty": 4,
      "question": "What does \"gracias\" mean?",
      "answer": "thank you",
      "translation": "thank you",
      "options": [
        "excuse me",
        "goodbye",
        "thank you",
        "hello"
      ]
    },
    {
      "id": "es-120-073",
      "word": "perdón",
      "pronunciation": "perdon",
      "english": "excuse me",
      "type": "vocabulary",
      "difficulty": 4,
      "question": "What does \"perdón\" mean?",
      "answer": "excuse me",
      "translation": "excuse me",
      "options": [
        "hello",
        "thank you",
        "excuse me",
        "goodbye"
      ]
    },
    {
      "id": "es-120-074",
      "word": "adiós",
      "pronunciation": "adios",
      "english": "goodbye",
      "type": "vocabulary",
      "difficulty": 4,
      "question": "What does \"adiós\" mean?",
      "answer": "goodbye",
      "translation": "goodbye",
      "options": [
        "thank you",
        "excuse me",
        "goodbye",
        "hello"
      ]
    },
    {
      "id": "es-120-075",
      "word": "estudiar",
      "pronunciation": "estudiar",
      "english": "to study",
      "type": "vocabulary",
      "difficulty": 4,
      "question": "What does \"estudiar\" mean?",
      "answer": "to study",
      "translation": "to study",
      "options": [
        "hello",
        "excuse me",
        "to study",
        "thank you"
      ]
    },
    {
      "id": "es-120-076",
      "word": "hola",
      "pronunciation": "ola",
      "english": "hello",
      "type": "vocabulary",
      "difficulty": 4,
      "question": "What does \"hola\" mean?",
      "answer": "hello",
      "translation": "hello",
      "options": [
        "goodbye",
        "excuse me",
        "thank you",
        "hello"
      ]
    },
    {
      "id": "es-120-077",
      "word": "gracias",
      "pronunciation": "gracias",
      "english": "thank you",
      "type": "vocabulary",
      "difficulty": 4,
      "question": "What does \"gracias\" mean?",
      "answer": "thank you",
      "translation": "thank you",
      "options": [
        "excuse me",
        "hello",
        "goodbye",
        "thank you"
      ]
    },
    {
      "id": "es-120-078",
      "word": "perdón",
      "pronunciation": "perdon",
      "english": "excuse me",
      "type": "vocabulary",
      "difficulty": 4,
      "question": "What does \"perdón\" mean?",
      "answer": "excuse me",
      "translation": "excuse me",
      "options": [
        "goodbye",
        "hello",
        "excuse me",
        "thank you"
      ]
    },
    {
      "id": "es-120-079",
      "word": "adiós",
      "pronunciation": "adios",
      "english": "goodbye",
      "type": "vocabulary",
      "difficulty": 4,
      "question": "What does \"adiós\" mean?",
      "answer": "goodbye",
      "translation": "goodbye",
      "options": [
        "excuse me",
        "thank you",
        "hello",
        "goodbye"
      ]
    },
    {
      "id": "es-120-080",
      "word": "estudiar",
      "pronunciation": "estudiar",
      "english": "to study",
      "type": "vocabulary",
      "difficulty": 4,
      "question": "What does \"estudiar\" mean?",
      "answer": "to study",
      "translation": "to study",
      "options": [
        "thank you",
        "hello",
        "to study",
        "excuse me"
      ]
    },
    {
      "id": "es-120-081",
      "word": "hola",
      "pronunciation": "ola",
      "english": "hello",
      "type": "vocabulary",
      "difficulty": 4,
      "question": "What does \"hola\" mean?",
      "answer": "hello",
      "translation": "hello",
      "options": [
        "goodbye",
        "thank you",
        "hello",
        "excuse me"
      ]
    },
    {
      "id": "es-120-082",
      "word": "gracias",
      "pronunciation": "gracias",
      "english": "thank you",
      "type": "vocabulary",
      "difficulty": 4,
      "question": "What does \"gracias\" mean?",
      "answer": "thank you",
      "translation": "thank you",
      "options": [
        "goodbye",
        "excuse me",
        "hello",
        "thank you"
      ]
    },
    {
      "id": "es-120-083",
      "word": "perdón",
      "pronunciation": "perdon",
      "english": "excuse me",
      "type": "vocabulary",
      "difficulty": 4,
      "question": "What does \"perdón\" mean?",
      "answer": "excuse me",
      "translation": "excuse me",
      "options": [
        "thank you",
        "excuse me",
        "goodbye",
        "hello"
      ]
    },
    {
      "id": "es-120-084",
      "word": "adiós",
      "pronunciation": "adios",
      "english": "goodbye",
      "type": "vocabulary",
      "difficulty": 4,
      "question": "What does \"adiós\" mean?",
      "answer": "goodbye",
      "translation": "goodbye",
      "options": [
        "hello",
        "excuse me",
        "thank you",
        "goodbye"
      ]
    },
    {
      "id": "es-120-085",
      "word": "estudiar",
      "pronunciation": "estudiar",
      "english": "to study",
      "type": "vocabulary",
      "difficulty": 4,
      "question": "What does \"estudiar\" mean?",
      "answer": "to study",
      "translation": "to study",
      "options": [
        "to study",
        "hello",
        "thank you",
        "excuse me"
      ]
    },
    {
      "id": "es-120-086",
      "word": "hola",
      "pronunciation": "ola",
      "english": "hello",
      "type": "vocabulary",
      "difficulty": 4,
      "question": "What does \"hola\" mean?",
      "answer": "hello",
      "translation": "hello",
      "options": [
        "excuse me",
        "goodbye",
        "thank you",
        "hello"
      ]
    },
    {
      "id": "es-120-087",
      "word": "gracias",
      "pronunciation": "gracias",
      "english": "thank you",
      "type": "vocabulary",
      "difficulty": 4,
      "question": "What does \"gracias\" mean?",
      "answer": "thank you",
      "translation": "thank you",
      "options": [
        "thank you",
        "hello",
        "excuse me",
        "goodbye"
      ]
    },
    {
      "id": "es-120-088",
      "word": "perdón",
      "pronunciation": "perdon",
      "english": "excuse me",
      "type": "vocabulary",
      "difficulty": 4,
      "question": "What does \"perdón\" mean?",
      "answer": "excuse me",
      "translation": "excuse me",
      "options": [
        "excuse me",
        "hello",
        "goodbye",
        "thank you"
      ]
    },
    {
      "id": "es-120-089",
      "word": "adiós",
      "pronunciation": "adios",
      "english": "goodbye",
      "type": "vocabulary",
      "difficulty": 4,
      "question": "What does \"adiós\" mean?",
      "answer": "goodbye",
      "translation": "goodbye",
      "options": [
        "excuse me",
        "thank you",
        "hello",
        "goodbye"
      ]
    },
    {
      "id": "es-120-090",
      "word": "estudiar",
      "pronunciation": "estudiar",
      "english": "to study",
      "type": "vocabulary",
      "difficulty": 4,
      "question": "What does \"estudiar\" mean?",
      "answer": "to study",
      "translation": "to study",
      "options": [
        "thank you",
        "hello",
        "to study",
        "excuse me"
      ]
    },
    {
      "id": "es-120-091",
      "word": "hola",
      "pronunciation": "ola",
      "english": "hello",
      "type": "vocabulary",
      "difficulty": 4,
      "question": "What does \"hola\" mean?",
      "answer": "hello",
      "translation": "hello",
      "options": [
        "goodbye",
        "excuse me",
        "thank you",
        "hello"
      ]
    },
    {
      "id": "es-120-092",
      "word": "gracias",
      "pronunciation": "gracias",
      "english": "thank you",
      "type": "vocabulary",
      "difficulty": 4,
      "question": "What does \"gracias\" mean?",
      "answer": "thank you",
      "translation": "thank you",
      "options": [
        "goodbye",
        "excuse me",
        "hello",
        "thank you"
      ]
    },
    {
      "id": "es-120-093",
      "word": "perdón",
      "pronunciation": "perdon",
      "english": "excuse me",
      "type": "vocabulary",
      "difficulty": 4,
      "question": "What does \"perdón\" mean?",
      "answer": "excuse me",
      "translation": "excuse me",
      "options": [
        "excuse me",
        "hello",
        "thank you",
        "goodbye"
      ]
    },
    {
      "id": "es-120-094",
      "word": "adiós",
      "pronunciation": "adios",
      "english": "goodbye",
      "type": "vocabulary",
      "difficulty": 4,
      "question": "What does \"adiós\" mean?",
      "answer": "goodbye",
      "translation": "goodbye",
      "options": [
        "goodbye",
        "hello",
        "excuse me",
        "thank you"
      ]
    },
    {
      "id": "es-120-095",
      "word": "estudiar",
      "pronunciation": "estudiar",
      "english": "to study",
      "type": "vocabulary",
      "difficulty": 4,
      "question": "What does \"estudiar\" mean?",
      "answer": "to study",
      "translation": "to study",
      "options": [
        "thank you",
        "excuse me",
        "hello",
        "to study"
      ]
    },
    {
      "id": "es-120-096",
      "word": "hola",
      "pronunciation": "ola",
      "english": "hello",
      "type": "vocabulary",
      "difficulty": 4,
      "question": "What does \"hola\" mean?",
      "answer": "hello",
      "translation": "hello",
      "options": [
        "hello",
        "thank you",
        "excuse me",
        "goodbye"
      ]
    },
    {
      "id": "es-120-097",
      "word": "gracias",
      "pronunciation": "gracias",
      "english": "thank you",
      "type": "vocabulary",
      "difficulty": 4,
      "question": "What does \"gracias\" mean?",
      "answer": "thank you",
      "translation": "thank you",
      "options": [
        "goodbye",
        "hello",
        "excuse me",
        "thank you"
      ]
    },
    {
      "id": "es-120-098",
      "word": "perdón",
      "pronunciation": "perdon",
      "english": "excuse me",
      "type": "vocabulary",
      "difficulty": 4,
      "question": "What does \"perdón\" mean?",
      "answer": "excuse me",
      "translation": "excuse me",
      "options": [
        "goodbye",
        "thank you",
        "hello",
        "excuse me"
      ]
    },
    {
      "id": "es-120-099",
      "word": "adiós",
      "pronunciation": "adios",
      "english": "goodbye",
      "type": "vocabulary",
      "difficulty": 4,
      "question": "What does \"adiós\" mean?",
      "answer": "goodbye",
      "translation": "goodbye",
      "options": [
        "excuse me",
        "goodbye",
        "hello",
        "thank you"
      ]
    },
    {
      "id": "es-120-100",
      "word": "estudiar",
      "pronunciation": "estudiar",
      "english": "to study",
      "type": "vocabulary",
      "difficulty": 4,
      "question": "What does \"estudiar\" mean?",
      "answer": "to study",
      "translation": "to study",
      "options": [
        "excuse me",
        "thank you",
        "hello",
        "to study"
      ]
    }
  ]
}