{
  "id": "ko-031",
  "title": "Beginner Lesson 31",
  "description": "Learn beginner level Korean",
  "language": "ko",
  "level": "beginner",
  "items": [
    {
      "id": "ko-031-001",
      "word": "안녕하세요",
      "romanization": "annyeonghaseyo",
      "english": "hello",
      "type": "vocabulary",
      "difficulty": 1,
      "question": "What does \"안녕하세요\" mean?",
      "answer": "hello",
      "translation": "hello",
      "options": [
        "goodbye (variant 4)",
        "hello",
        "thank you (variant 2)",
        "sorry (variant 3)"
      ],
      "pronunciation": "annyeonghaseyo"
    },
    {
      "id": "ko-031-002",
      "word": "감사합니다",
      "romanization": "gamsahamnida",
      "english": "thank you",
      "type": "vocabulary",
      "difficulty": 1,
      "question": "What does \"감사합니다\" mean?",
      "answer": "thank you",
      "translation": "thank you",
      "options": [
        "thank you",
        "hello",
        "sorry (variant 3)",
        "goodbye (variant 4)"
      ],
      "pronunciation": "gamsahamnida"
    },
    {
      "id": "ko-031-003",
      "word": "죄송합니다",
      "romanization": "joesonghamnida",
      "english": "sorry",
      "type": "vocabulary",
      "difficulty": 1,
      "question": "What does \"죄송합니다\" mean?",
      "answer": "sorry",
      "translation": "sorry",
      "options": [
        "goodbye (variant 4)",
        "thank you",
        "hello",
        "sorry"
      ],
      "pronunciation": "joesonghamnida"
    },
    {
      "id": "ko-031-004",
      "word": "안녕히 가세요",
      "romanization": "annyeonghi gaseyo",
      "english": "goodbye",
      "type": "vocabulary",
      "difficulty": 1,
      "question": "What does \"안녕히 가세요\" mean?",
      "answer": "goodbye",
      "translation": "goodbye",
      "options": [
        "goodbye",
        "hello",
        "thank you",
        "sorry"
      ],
      "pronunciation": "annyeonghi gaseyo"
    },
    {
      "id": "ko-031-005",
      "word": "공부하다",
      "romanization": "gongbuhada",
      "english": "to study",
      "type": "vocabulary",
      "difficulty": 1,
      "question": "What does \"공부하다\" mean?",
      "answer": "to study",
      "translation": "to study",
      "options": [
        "to study",
        "sorry",
        "hello",
        "thank you"
      ],
      "pronunciation": "gongbuhada"
    },
    {
      "id": "ko-031-006",
      "word": "안녕하세요",
      "romanization": "annyeonghaseyo",
      "english": "hello",
      "type": "vocabulary",
      "difficulty": 1,
      "question": "What does \"안녕하세요\" mean?",
      "answer": "hello",
      "translation": "hello",
      "options": [
        "sorry",
        "thank you",
        "goodbye",
        "hello"
      ],
      "pronunciation": "annyeonghaseyo"
    },
    {
      "id": "ko-031-007",
      "word": "감사합니다",
      "romanization": "gamsahamnida",
      "english": "thank you",
      "type": "vocabulary",
      "difficulty": 1,
      "question": "What does \"감사합니다\" mean?",
      "answer": "thank you",
      "translation": "thank you",
      "options": [
        "goodbye",
        "sorry",
        "hello",
        "thank you"
      ],
      "pronunciation": "gamsahamnida"
    },
    {
      "id": "ko-031-008",
      "word": "죄송합니다",
      "romanization": "joesonghamnida",
      "english": "sorry",
      "type": "vocabulary",
      "difficulty": 1,
      "question": "What does \"죄송합니다\" mean?",
      "answer": "sorry",
      "translation": "sorry",
      "options": [
        "hello",
        "thank you",
        "goodbye",
        "sorry"
      ],
      "pronunciation": "joesonghamnida"
    },
    {
      "id": "ko-031-009",
      "word": "안녕히 가세요",
      "romanization": "annyeonghi gaseyo",
      "english": "goodbye",
      "type": "vocabulary",
      "difficulty": 1,
      "question": "What does \"안녕히 가세요\" mean?",
      "answer": "goodbye",
      "translation": "goodbye",
      "options": [
        "hello",
        "goodbye",
        "sorry",
        "thank you"
      ],
      "pronunciation": "annyeonghi gaseyo"
    },
    {
      "id": "ko-031-010",
      "word": "공부하다",
      "romanization": "gongbuhada",
      "english": "to study",
      "type": "vocabulary",
      "difficulty": 1,
      "question": "What does \"공부하다\" mean?",
      "answer": "to study",
      "translation": "to study",
      "options": [
        "sorry",
        "thank you",
        "hello",
        "to study"
      ],
      "pronunciation": "gongbuhada"
    },
    {
      "id": "ko-031-011",
      "word": "안녕하세요",
      "romanization": "annyeonghaseyo",
      "english": "hello",
      "type": "vocabulary",
      "difficulty": 1,
      "question": "What does \"안녕하세요\" mean?",
      "answer": "hello",
      "translation": "hello",
      "options": [
        "goodbye",
        "hello",
        "thank you",
        "sorry"
      ],
      "pronunciation": "annyeonghaseyo"
    },
    {
      "id": "ko-031-012",
      "word": "감사합니다",
      "romanization": "gamsahamnida",
      "english": "thank you",
      "type": "vocabulary",
      "difficulty": 1,
      "question": "What does \"감사합니다\" mean?",
      "answer": "thank you",
      "translation": "thank you",
      "options": [
        "goodbye",
        "thank you",
        "hello",
        "sorry"
      ],
      "pronunciation": "gamsahamnida"
    },
    {
      "id": "ko-031-013",
      "word": "죄송합니다",
      "romanization": "joesonghamnida",
      "english": "sorry",
      "type": "vocabulary",
      "difficulty": 1,
      "question": "What does \"죄송합니다\" mean?",
      "answer": "sorry",
      "translation": "sorry",
      "options": [
        "hello",
        "sorry",
        "thank you",
        "goodbye"
      ],
      "pronunciation": "joesonghamnida"
    },
    {
      "id": "ko-031-014",
      "word": "안녕히 가세요",
      "romanization": "annyeonghi gaseyo",
      "english": "goodbye",
      "type": "vocabulary",
      "difficulty": 1,
      "question": "What does \"안녕히 가세요\" mean?",
      "answer": "goodbye",
      "translation": "goodbye",
      "options": [
        "thank you",
        "sorry",
        "hello",
        "goodbye"
      ],
      "pronunciation": "annyeonghi gaseyo"
    },
    {
      "id": "ko-031-015",
      "word": "공부하다",
      "romanization": "gongbuhada",
      "english": "to study",
      "type": "vocabulary",
      "difficulty": 1,
      "question": "What does \"공부하다\" mean?",
      "answer": "to study",
      "translation": "to study",
      "options": [
        "to study",
        "hello",
        "thank you",
        "sorry"
      ],
      "pronunciation": "gongbuhada"
    },
    {
      "id": "ko-031-016",
      "word": "안녕하세요",
      "romanization": "annyeonghaseyo",
      "english": "hello",
      "type": "vocabulary",
      "difficulty": 1,
      "question": "What does \"안녕하세요\" mean?",
      "answer": "hello",
      "translation": "hello",
      "options": [
        "sorry",
        "thank you",
        "hello",
        "goodbye"
      ],
      "pronunciation": "annyeonghaseyo"
    },
    {
      "id": "ko-031-017",
      "word": "감사합니다",
      "romanization": "gamsahamnida",
      "english": "thank you",
      "type": "vocabulary",
      "difficulty": 1,
      "question": "What does \"감사합니다\" mean?",
      "answer": "thank you",
      "translation": "thank you",
      "options": [
        "goodbye",
        "sorry",
        "hello",
        "thank you"
      ],
      "pronunciation": "gamsahamnida"
    },
    {
      "id": "ko-031-018",
      "word": "죄송합니다",
      "romanization": "joesonghamnida",
      "english": "sorry",
      "type": "vocabulary",
      "difficulty": 1,
      "question": "What does \"죄송합니다\" mean?",
      "answer": "sorry",
      "translation": "sorry",
      "options": [
        "hello",
        "sorry",
        "goodbye",
        "thank you"
      ],
      "pronunciation": "joesonghamnida"
    },
    {
      "id": "ko-031-019",
      "word": "안녕히 가세요",
      "romanization": "annyeonghi gaseyo",
      "english": "goodbye",
      "type": "vocabulary",
      "difficulty": 1,
      "question": "What does \"안녕히 가세요\" mean?",
      "answer": "goodbye",
      "translation": "goodbye",
      "options": [
        "thank you",
        "hello",
        "goodbye",
        "sorry"
      ],
      "pronunciation": "annyeonghi gaseyo"
    },
    {
      "id": "ko-031-020",
      "word": "공부하다",
      "romanization": "gongbuhada",
      "english": "to study",
      "type": "vocabulary",
      "difficulty": 1,
      "question": "What does \"공부하다\" mean?",
      "answer": "to study",
      "translation": "to study",
      "options": [
        "sorry",
        "to study",
        "hello",
        "thank you"
      ],
      "pronunciation": "gongbuhada"
    },
    {
      "id": "ko-031-021",
      "word": "안녕하세요",
      "romanization": "annyeonghaseyo",
      "english": "hello",
      "type": "vocabulary",
      "difficulty": 1,
      "question": "What does \"안녕하세요\" mean?",
      "answer": "hello",
      "translation": "hello",
      "options": [
        "goodbye",
        "hello",
        "thank you",
        "sorry"
      ],
      "pronunciation": "annyeonghaseyo"
    },
    {
      "id": "ko-031-022",
      "word": "감사합니다",
      "romanization": "gamsahamnida",
      "english": "thank you",
      "type": "vocabulary",
      "difficulty": 1,
      "question": "What does \"감사합니다\" mean?",
      "answer": "thank you",
      "translation": "thank you",
      "options": [
        "sorry",
        "goodbye",
        "hello",
        "thank you"
      ],
      "pronunciation": "gamsahamnida"
    },
    {
      "id": "ko-031-023",
      "word": "죄송합니다",
      "romanization": "joesonghamnida",
      "english": "sorry",
      "type": "vocabulary",
      "difficulty": 1,
      "question": "What does \"죄송합니다\" mean?",
      "answer": "sorry",
      "translation": "sorry",
      "options": [
        "sorry",
        "goodbye",
        "hello",
        "thank you"
      ],
      "pronunciation": "joesonghamnida"
    },
    {
      "id": "ko-031-024",
      "word": "안녕히 가세요",
      "romanization": "annyeonghi gaseyo",
      "english": "goodbye",
      "type": "vocabulary",
      "difficulty": 1,
      "question": "What does \"안녕히 가세요\" mean?",
      "answer": "goodbye",
      "translation": "goodbye",
      "options": [
        "sorry",
        "goodbye",
        "hello",
        "thank you"
      ],
      "pronunciation": "annyeonghi gaseyo"
    },
    {
      "id": "ko-031-025",
      "word": "공부하다",
      "romanization": "gongbuhada",
      "english": "to study",
      "type": "vocabulary",
      "difficulty": 1,
      "question": "What does \"공부하다\" mean?",
      "answer": "to study",
      "translation": "to study",
      "options": [
        "to study",
        "hello",
        "thank you",
        "sorry"
      ],
      "pronunciation": "gongbuhada"
    },
    {
      "id": "ko-031-026",
      "word": "안녕하세요",
      "romanization": "annyeonghaseyo",
      "english": "hello",
      "type": "vocabulary",
      "difficulty": 1,
      "question": "What does \"안녕하세요\" mean?",
      "answer": "hello",
      "translation": "hello",
      "options": [
        "hello",
        "goodbye",
        "thank you",
        "sorry"
      ],
      "pronunciation": "annyeonghaseyo"
    },
    {
      "id": "ko-031-027",
      "word": "감사합니다",
      "romanization": "gamsahamnida",
      "english": "thank you",
      "type": "vocabulary",
      "difficulty": 1,
      "question": "What does \"감사합니다\" mean?",
      "answer": "thank you",
      "translation": "thank you",
      "options": [
        "sorry",
        "hello",
        "goodbye",
        "thank you"
      ],
      "pronunciation": "gamsahamnida"
    },
    {
      "id": "ko-031-028",
      "word": "죄송합니다",
      "romanization": "joesonghamnida",
      "english": "sorry",
      "type": "vocabulary",
      "difficulty": 1,
      "question": "What does \"죄송합니다\" mean?",
      "answer": "sorry",
      "translation": "sorry",
      "options": [
        "goodbye",
        "thank you",
        "hello",
        "sorry"
      ],
      "pronunciation": "joesonghamnida"
    },
    {
      "id": "ko-031-029",
      "word": "안녕히 가세요",
      "romanization": "annyeonghi gaseyo",
      "english": "goodbye",
      "type": "vocabulary",
      "difficulty": 1,
      "question": "What does \"안녕히 가세요\" mean?",
      "answer": "goodbye",
      "translation": "goodbye",
      "options": [
        "sorry",
        "goodbye",
        "hello",
        "thank you"
      ],
      "pronunciation": "annyeonghi gaseyo"
    },
    {
      "id": "ko-031-030",
      "word": "공부하다",
      "romanization": "gongbuhada",
      "english": "to study",
      "type": "vocabulary",
      "difficulty": 1,
      "question": "What does \"공부하다\" mean?",
      "answer": "to study",
      "translation": "to study",
      "options": [
        "sorry",
        "to study",
        "hello",
        "thank you"
      ],
      "pronunciation": "gongbuhada"
    },
    {
      "id": "ko-031-031",
      "word": "안녕하세요",
      "romanization": "annyeonghaseyo",
      "english": "hello",
      "type": "vocabulary",
      "difficulty": 1,
      "question": "What does \"안녕하세요\" mean?",
      "answer": "hello",
      "translation": "hello",
      "options": [
        "thank you",
        "sorry",
        "goodbye",
        "hello"
      ],
      "pronunciation": "annyeonghaseyo"
    },
    {
      "id": "ko-031-032",
      "word": "감사합니다",
      "romanization": "gamsahamnida",
      "english": "thank you",
      "type": "vocabulary",
      "difficulty": 1,
      "question": "What does \"감사합니다\" mean?",
      "answer": "thank you",
      "translation": "thank you",
      "options": [
        "goodbye",
        "sorry",
        "hello",
        "thank you"
      ],
      "pronunciation": "gamsahamnida"
    },
    {
      "id": "ko-031-033",
      "word": "죄송합니다",
      "romanization": "joesonghamnida",
      "english": "sorry",
      "type": "vocabulary",
      "difficulty": 1,
      "question": "What does \"죄송합니다\" mean?",
      "answer": "sorry",
      "translation": "sorry",
      "options": [
        "thank you",
        "goodbye",
        "hello",
        "sorry"
      ],
      "pronunciation": "joesonghamnida"
    },
    {
      "id": "ko-031-034",
      "word": "안녕히 가세요",
      "romanization": "annyeonghi gaseyo",
      "english": "goodbye",
      "type": "vocabulary",
      "difficulty": 1,
      "question": "What does \"안녕히 가세요\" mean?",
      "answer": "goodbye",
      "translation": "goodbye",
      "options": [
        "sorry",
        "thank you",
        "hello",
        "goodbye"
      ],
      "pronunciation": "annyeonghi gaseyo"
    },
    {
      "id": "ko-031-035",
      "word": "공부하다",
      "romanization": "gongbuhada",
      "english": "to study",
      "type": "vocabulary",
      "difficulty": 1,
      "question": "What does \"공부하다\" mean?",
      "answer": "to study",
      "translation": "to study",
      "options": [
        "to study",
        "hello",
        "sorry",
        "thank you"
      ],
      "pronunciation": "gongbuhada"
    },
    {
      "id": "ko-031-036",
      "word": "안녕하세요",
      "romanization": "annyeonghaseyo",
      "english": "hello",
      "type": "vocabulary",
      "difficulty": 1,
      "question": "What does \"안녕하세요\" mean?",
      "answer": "hello",
      "translation": "hello",
      "options": [
        "hello",
        "thank you",
        "sorry",
        "goodbye"
      ],
      "pronunciation": "annyeonghaseyo"
    },
    {
      "id": "ko-031-037",
      "word": "감사합니다",
      "romanization": "gamsahamnida",
      "english": "thank you",
      "type": "vocabulary",
      "difficulty": 1,
      "question": "What does \"감사합니다\" mean?",
      "answer": "thank you",
      "translation": "thank you",
      "options": [
        "thank you",
        "goodbye",
        "hello",
        "sorry"
      ],
      "pronunciation": "gamsahamnida"
    },
    {
      "id": "ko-031-038",
      "word": "죄송합니다",
      "romanization": "joesonghamnida",
      "english": "sorry",
      "type": "vocabulary",
      "difficulty": 1,
      "question": "What does \"죄송합니다\" mean?",
      "answer": "sorry",
      "translation": "sorry",
      "options": [
        "sorry",
        "hello",
        "thank you",
        "goodbye"
      ],
      "pronunciation": "joesonghamnida"
    },
    {
      "id": "ko-031-039",
      "word": "안녕히 가세요",
      "romanization": "annyeonghi gaseyo",
      "english": "goodbye",
      "type": "vocabulary",
      "difficulty": 1,
      "question": "What does \"안녕히 가세요\" mean?",
      "answer": "goodbye",
      "translation": "goodbye",
      "options": [
        "hello",
        "sorry",
        "thank you",
        "goodbye"
      ],
      "pronunciation": "annyeonghi gaseyo"
    },
    {
      "id": "ko-031-040",
      "word": "공부하다",
      "romanization": "gongbuhada",
      "english": "to study",
      "type": "vocabulary",
      "difficulty": 1,
      "question": "What does \"공부하다\" mean?",
      "answer": "to study",
      "translation": "to study",
      "options": [
        "sorry",
        "thank you",
        "to study",
        "hello"
      ],
      "pronunciation": "gongbuhada"
    },
    {
      "id": "ko-031-041",
      "word": "안녕하세요",
      "romanization": "annyeonghaseyo",
      "english": "hello",
      "type": "vocabulary",
      "difficulty": 1,
      "question": "What does \"안녕하세요\" mean?",
      "answer": "hello",
      "translation": "hello",
      "options": [
        "thank you",
        "hello",
        "goodbye",
        "sorry"
      ],
      "pronunciation": "annyeonghaseyo"
    },
    {
      "id": "ko-031-042",
      "word": "감사합니다",
      "romanization": "gamsahamnida",
      "english": "thank you",
      "type": "vocabulary",
      "difficulty": 1,
      "question": "What does \"감사합니다\" mean?",
      "answer": "thank you",
      "translation": "thank you",
      "options": [
        "sorry",
        "goodbye",
        "hello",
        "thank you"
      ],
      "pronunciation": "gamsahamnida"
    },
    {
      "id": "ko-031-043",
      "word": "죄송합니다",
      "romanization": "joesonghamnida",
      "english": "sorry",
      "type": "vocabulary",
      "difficulty": 1,
      "question": "What does \"죄송합니다\" mean?",
      "answer": "sorry",
      "translation": "sorry",
      "options": [
        "sorry",
        "hello",
        "goodbye",
        "thank you"
      ],
      "pronunciation": "joesonghamnida"
    },
    {
      "id": "ko-031-044",
      "word": "안녕히 가세요",
      "romanization": "annyeonghi gaseyo",
      "english": "goodbye",
      "type": "vocabulary",
      "difficulty": 1,
      "question": "What does \"안녕히 가세요\" mean?",
      "answer": "goodbye",
      "translation": "goodbye",
      "options": [
        "hello",
        "thank you",
        "goodbye",
        "sorry"
      ],
      "pronunciation": "annyeonghi gaseyo"
    },
    {
      "id": "ko-031-045",
      "word": "공부하다",
      "romanization": "gongbuhada",
      "english": "to study",
      "type": "vocabulary",
      "difficulty": 1,
      "question": "What does \"공부하다\" mean?",
      "answer": "to study",
      "translation": "to study",
      "options": [
        "thank you",
        "hello",
        "sorry",
        "to study"
      ],
      "pronunciation": "gongbuhada"
    },
    {
      "id": "ko-031-046",
      "word": "안녕하세요",
      "romanization": "annyeonghaseyo",
      "english": "hello",
      "type": "vocabulary",
      "difficulty": 1,
      "question": "What does \"안녕하세요\" mean?",
      "answer": "hello",
      "translation": "hello",
      "options": [
        "hello",
        "thank you",
        "sorry",
        "goodbye"
      ],
      "pronunciation": "annyeonghaseyo"
    },
    {
      "id": "ko-031-047",
      "word": "감사합니다",
      "romanization": "gamsahamnida",
      "english": "thank you",
      "type": "vocabulary",
      "difficulty": 1,
      "question": "What does \"감사합니다\" mean?",
      "answer": "thank you",
      "translation": "thank you",
      "options": [
        "goodbye",
        "sorry",
        "hello",
        "thank you"
      ],
      "pronunciation": "gamsahamnida"
    },
    {
      "id": "ko-031-048",
      "word": "죄송합니다",
      "romanization": "joesonghamnida",
      "english": "sorry",
      "type": "vocabulary",
      "difficulty": 1,
      "question": "What does \"죄송합니다\" mean?",
      "answer": "sorry",
      "translation": "sorry",
      "options": [
        "hello",
        "goodbye",
        "thank you",
        "sorry"
      ],
      "pronunciation": "joesonghamnida"
    },
    {
      "id": "ko-031-049",
      "word": "안녕히 가세요",
      "romanization": "annyeonghi gaseyo",
      "english": "goodbye",
      "type": "vocabulary",
      "difficulty": 1,
      "question": "What does \"안녕히 가세요\" mean?",
      "answer": "goodbye",
      "translation": "goodbye",
      "options": [
        "hello",
        "thank you",
        "goodbye",
        "sorry"
      ],
      "pronunciation": "annyeonghi gaseyo"
    },
    {
      "id": "ko-031-050",
      "word": "공부하다",
      "romanization": "gongbuhada",
      "english": "to study",
      "type": "vocabulary",
      "difficulty": 1,
      "question": "What does \"공부하다\" mean?",
      "answer": "to study",
      "translation": "to study",
      "options": [
        "to study",
        "hello",
        "sorry",
        "thank you"
      ],
      "pronunciation": "gongbuhada"
    },
    {
      "id": "ko-031-051",
      "word": "안녕하세요",
      "romanization": "annyeonghaseyo",
      "english": "hello",
      "type": "vocabulary",
      "difficulty": 1,
      "question": "What does \"안녕하세요\" mean?",
      "answer": "hello",
      "translation": "hello",
      "options": [
        "goodbye",
        "sorry",
        "thank you",
        "hello"
      ],
      "pronunciation": "annyeonghaseyo"
    },
    {
      "id": "ko-031-052",
      "word": "감사합니다",
      "romanization": "gamsahamnida",
      "english": "thank you",
      "type": "vocabulary",
      "difficulty": 1,
      "question": "What does \"감사합니다\" mean?",
      "answer": "thank you",
      "translation": "thank you",
      "options": [
        "thank you",
        "hello",
        "sorry",
        "goodbye"
      ],
      "pronunciation": "gamsahamnida"
    },
    {
      "id": "ko-031-053",
      "word": "죄송합니다",
      "romanization": "joesonghamnida",
      "english": "sorry",
      "type": "vocabulary",
      "difficulty": 1,
      "question": "What does \"죄송합니다\" mean?",
      "answer": "sorry",
      "translation": "sorry",
      "options": [
        "sorry",
        "hello",
        "thank you",
        "goodbye"
      ],
      "pronunciation": "joesonghamnida"
    },
    {
      "id": "ko-031-054",
      "word": "안녕히 가세요",
      "romanization": "annyeonghi gaseyo",
      "english": "goodbye",
      "type": "vocabulary",
      "difficulty": 1,
      "question": "What does \"안녕히 가세요\" mean?",
      "answer": "goodbye",
      "translation": "goodbye",
      "options": [
        "sorry",
        "goodbye",
        "hello",
        "thank you"
      ],
      "pronunciation": "annyeonghi gaseyo"
    },
    {
      "id": "ko-031-055",
      "word": "공부하다",
      "romanization": "gongbuhada",
      "english": "to study",
      "type": "vocabulary",
      "difficulty": 1,
      "question": "What does \"공부하다\" mean?",
      "answer": "to study",
      "translation": "to study",
      "options": [
        "to study",
        "hello",
        "thank you",
        "sorry"
      ],
      "pronunciation": "gongbuhada"
    },
    {
      "id": "ko-031-056",
      "word": "안녕하세요",
      "romanization": "annyeonghaseyo",
      "english": "hello",
      "type": "vocabulary",
      "difficulty": 1,
      "question": "What does \"안녕하세요\" mean?",
      "answer": "hello",
      "translation": "hello",
      "options": [
        "goodbye",
        "hello",
        "thank you",
        "sorry"
      ],
      "pronunciation": "annyeonghaseyo"
    },
    {
      "id": "ko-031-057",
      "word": "감사합니다",
      "romanization": "gamsahamnida",
      "english": "thank you",
      "type": "vocabulary",
      "difficulty": 1,
      "question": "What does \"감사합니다\" mean?",
      "answer": "thank you",
      "translation": "thank you",
      "options": [
        "thank you",
        "hello",
        "goodbye",
        "sorry"
      ],
      "pronunciation": "gamsahamnida"
    },
    {
      "id": "ko-031-058",
      "word": "죄송합니다",
      "romanization": "joesonghamnida",
      "english": "sorry",
      "type": "vocabulary",
      "difficulty": 1,
      "question": "What does \"죄송합니다\" mean?",
      "answer": "sorry",
      "translation": "sorry",
      "options": [
        "goodbye",
        "thank you",
        "hello",
        "sorry"
      ],
      "pronunciation": "joesonghamnida"
    },
    {
      "id": "ko-031-059",
      "word": "안녕히 가세요",
      "romanization": "annyeonghi gaseyo",
      "english": "goodbye",
      "type": "vocabulary",
      "difficulty": 1,
      "question": "What does \"안녕히 가세요\" mean?",
      "answer": "goodbye",
      "translation": "goodbye",
      "options": [
        "thank you",
        "hello",
        "goodbye",
        "sorry"
      ],
      "pronunciation": "annyeonghi gaseyo"
    },
    {
      "id": "ko-031-060",
      "word": "공부하다",
      "romanization": "gongbuhada",
      "english": "to study",
      "type": "vocabulary",
      "difficulty": 1,
      "question": "What does \"공부하다\" mean?",
      "answer": "to study",
      "translation": "to study",
      "options": [
        "thank you",
        "hello",
        "to study",
        "sorry"
      ],
      "pronunciation": "gongbuhada"
    },
    {
      "id": "ko-031-061",
      "word": "안녕하세요",
      "romanization": "annyeonghaseyo",
      "english": "hello",
      "type": "vocabulary",
      "difficulty": 1,
      "question": "What does \"안녕하세요\" mean?",
      "answer": "hello",
      "translation": "hello",
      "options": [
        "hello",
        "goodbye",
        "thank you",
        "sorry"
      ],
      "pronunciation": "annyeonghaseyo"
    },
    {
      "id": "ko-031-062",
      "word": "감사합니다",
      "romanization": "gamsahamnida",
      "english": "thank you",
      "type": "vocabulary",
      "difficulty": 1,
      "question": "What does \"감사합니다\" mean?",
      "answer": "thank you",
      "translation": "thank you",
      "options": [
        "sorry",
        "hello",
        "thank you",
        "goodbye"
      ],
      "pronunciation": "gamsahamnida"
    },
    {
      "id": "ko-031-063",
      "word": "죄송합니다",
      "romanization": "joesonghamnida",
      "english": "sorry",
      "type": "vocabulary",
      "difficulty": 1,
      "question": "What does \"죄송합니다\" mean?",
      "answer": "sorry",
      "translation": "sorry",
      "options": [
        "goodbye",
        "sorry",
        "thank you",
        "hello"
      ],
      "pronunciation": "joesonghamnida"
    },
    {
      "id": "ko-031-064",
      "word": "안녕히 가세요",
      "romanization": "annyeonghi gaseyo",
      "english": "goodbye",
      "type": "vocabulary",
      "difficulty": 1,
      "question": "What does \"안녕히 가세요\" mean?",
      "answer": "goodbye",
      "translation": "goodbye",
      "options": [
        "sorry",
        "thank you",
        "hello",
        "goodbye"
      ],
      "pronunciation": "annyeonghi gaseyo"
    },
    {
      "id": "ko-031-065",
      "word": "공부하다",
      "romanization": "gongbuhada",
      "english": "to study",
      "type": "vocabulary",
      "difficulty": 1,
      "question": "What does \"공부하다\" mean?",
      "answer": "to study",
      "translation": "to study",
      "options": [
        "to study",
        "thank you",
        "sorry",
        "hello"
      ],
      "pronunciation": "gongbuhada"
    },
    {
      "id": "ko-031-066",
      "word": "안녕하세요",
      "romanization": "annyeonghaseyo",
      "english": "hello",
      "type": "vocabulary",
      "difficulty": 1,
      "question": "What does \"안녕하세요\" mean?",
      "answer": "hello",
      "translation": "hello",
      "options": [
        "goodbye",
        "hello",
        "thank you",
        "sorry"
      ],
      "pronunciation": "annyeonghaseyo"
    },
    {
      "id": "ko-031-067",
      "word": "감사합니다",
      "romanization": "gamsahamnida",
      "english": "thank you",
      "type": "vocabulary",
      "difficulty": 1,
      "question": "What does \"감사합니다\" mean?",
      "answer": "thank you",
      "translation": "thank you",
      "options": [
        "thank you",
        "hello",
        "sorry",
        "goodbye"
      ],
      "pronunciation": "gamsahamnida"
    },
    {
      "id": "ko-031-068",
      "word": "죄송합니다",
      "romanization": "joesonghamnida",
      "english": "sorry",
      "type": "vocabulary",
      "difficulty": 1,
      "question": "What does \"죄송합니다\" mean?",
      "answer": "sorry",
      "translation": "sorry",
      "options": [
        "sorry",
        "hello",
        "thank you",
        "goodbye"
      ],
      "pronunciation": "joesonghamnida"
    },
    {
      "id": "ko-031-069",
      "word": "안녕히 가세요",
      "romanization": "annyeonghi gaseyo",
      "english": "goodbye",
      "type": "vocabulary",
      "difficulty": 1,
      "question": "What does \"안녕히 가세요\" mean?",
      "answer": "goodbye",
      "translation": "goodbye",
      "options": [
        "goodbye",
        "sorry",
        "hello",
        "thank you"
      ],
      "pronunciation": "annyeonghi gaseyo"
    },
    {
      "id": "ko-031-070",
      "word": "공부하다",
      "romanization": "gongbuhada",
      "english": "to study",
      "type": "vocabulary",
      "difficulty": 1,
      "question": "What does \"공부하다\" mean?",
      "answer": "to study",
      "translation": "to study",
      "options": [
        "to study",
        "hello",
        "sorry",
        "thank you"
      ],
      "pronunciation": "gongbuhada"
    },
    {
      "id": "ko-031-071",
      "word": "안녕하세요",
      "romanization": "annyeonghaseyo",
      "english": "hello",
      "type": "vocabulary",
      "difficulty": 1,
      "question": "What does \"안녕하세요\" mean?",
      "answer": "hello",
      "translation": "hello",
      "options": [
        "thank you",
        "hello",
        "sorry",
        "goodbye"
      ],
      "pronunciation": "annyeonghaseyo"
    },
    {
      "id": "ko-031-072",
      "word": "감사합니다",
      "romanization": "gamsahamnida",
      "english": "thank you",
      "type": "vocabulary",
      "difficulty": 1,
      "question": "What does \"감사합니다\" mean?",
      "answer": "thank you",
      "translation": "thank you",
      "options": [
        "hello",
        "goodbye",
        "thank you",
        "sorry"
      ],
      "pronunciation": "gamsahamnida"
    },
    {
      "id": "ko-031-073",
      "word": "죄송합니다",
      "romanization": "joesonghamnida",
      "english": "sorry",
      "type": "vocabulary",
      "difficulty": 1,
      "question": "What does \"죄송합니다\" mean?",
      "answer": "sorry",
      "translation": "sorry",
      "options": [
        "sorry",
        "hello",
        "thank you",
        "goodbye"
      ],
      "pronunciation": "joesonghamnida"
    },
    {
      "id": "ko-031-074",
      "word": "안녕히 가세요",
      "romanization": "annyeonghi gaseyo",
      "english": "goodbye",
      "type": "vocabulary",
      "difficulty": 1,
      "question": "What does \"안녕히 가세요\" mean?",
      "answer": "goodbye",
      "translation": "goodbye",
      "options": [
        "goodbye",
        "hello",
        "sorry",
        "thank you"
      ],
      "pronunciation": "annyeonghi gaseyo"
    },
    {
      "id": "ko-031-075",
      "word": "공부하다",
      "romanization": "gongbuhada",
      "english": "to study",
      "type": "vocabulary",
      "difficulty": 1,
      "question": "What does \"공부하다\" mean?",
      "answer": "to study",
      "translation": "to study",
      "options": [
        "sorry",
        "to study",
        "thank you",
        "hello"
      ],
      "pronunciation": "gongbuhada"
    },
    {
      "id": "ko-031-076",
      "word": "안녕하세요",
      "romanization": "annyeonghaseyo",
      "english": "hello",
      "type": "vocabulary",
      "difficulty": 1,
      "question": "What does \"안녕하세요\" mean?",
      "answer": "hello",
      "translation": "hello",
      "options": [
        "hello",
        "thank you",
        "goodbye",
        "sorry"
      ],
      "pronunciation": "annyeonghaseyo"
    },
    {
      "id": "ko-031-077",
      "word": "감사합니다",
      "romanization": "gamsahamnida",
      "english": "thank you",
      "type": "vocabulary",
      "difficulty": 1,
      "question": "What does \"감사합니다\" mean?",
      "answer": "thank you",
      "translation": "thank you",
      "options": [
        "sorry",
        "hello",
        "thank you",
        "goodbye"
      ],
      "pronunciation": "gamsahamnida"
    },
    {
      "id": "ko-031-078",
      "word": "죄송합니다",
      "romanization": "joesonghamnida",
      "english": "sorry",
      "type": "vocabulary",
      "difficulty": 1,
      "question": "What does \"죄송합니다\" mean?",
      "answer": "sorry",
      "translation": "sorry",
      "options": [
        "sorry",
        "goodbye",
        "hello",
        "thank you"
      ],
      "pronunciation": "joesonghamnida"
    },
    {
      "id": "ko-031-079",
      "word": "안녕히 가세요",
      "romanization": "annyeonghi gaseyo",
      "english": "goodbye",
      "type": "vocabulary",
      "difficulty": 1,
      "question": "What does \"안녕히 가세요\" mean?",
      "answer": "goodbye",
      "translation": "goodbye",
      "options": [
        "hello",
        "thank you",
        "goodbye",
        "sorry"
      ],
      "pronunciation": "annyeonghi gaseyo"
    },
    {
      "id": "ko-031-080",
      "word": "공부하다",
      "romanization": "gongbuhada",
      "english": "to study",
      "type": "vocabulary",
      "difficulty": 1,
      "question": "What does \"공부하다\" mean?",
      "answer": "to study",
      "translation": "to study",
      "options": [
        "to study",
        "hello",
        "thank you",
        "sorry"
      ],
      "pronunciation": "gongbuhada"
    },
    {
      "id": "ko-031-081",
      "word": "안녕하세요",
      "romanization": "annyeonghaseyo",
      "english": "hello",
      "type": "vocabulary",
      "difficulty": 1,
      "question": "What does \"안녕하세요\" mean?",
      "answer": "hello",
      "translation": "hello",
      "options": [
        "goodbye",
        "thank you",
        "hello",
        "sorry"
      ],
      "pronunciation": "annyeonghaseyo"
    },
    {
      "id": "ko-031-082",
      "word": "감사합니다",
      "romanization": "gamsahamnida",
      "english": "thank you",
      "type": "vocabulary",
      "difficulty": 1,
      "question": "What does \"감사합니다\" mean?",
      "answer": "thank you",
      "translation": "thank you",
      "options": [
        "goodbye",
        "sorry",
        "hello",
        "thank you"
      ],
      "pronunciation": "gamsahamnida"
    },
    {
      "id": "ko-031-083",
      "word": "죄송합니다",
      "romanization": "joesonghamnida",
      "english": "sorry",
      "type": "vocabulary",
      "difficulty": 1,
      "question": "What does \"죄송합니다\" mean?",
      "answer": "sorry",
      "translation": "sorry",
      "options": [
        "thank you",
        "hello",
        "sorry",
        "goodbye"
      ],
      "pronunciation": "joesonghamnida"
    },
    {
      "id": "ko-031-084",
      "word": "안녕히 가세요",
      "romanization": "annyeonghi gaseyo",
      "english": "goodbye",
      "type": "vocabulary",
      "difficulty": 1,
      "question": "What does \"안녕히 가세요\" mean?",
      "answer": "goodbye",
      "translation": "goodbye",
      "options": [
        "goodbye",
        "thank you",
        "hello",
        "sorry"
      ],
      "pronunciation": "annyeonghi gaseyo"
    },
    {
      "id": "ko-031-085",
      "word": "공부하다",
      "romanization": "gongbuhada",
      "english": "to study",
      "type": "vocabulary",
      "difficulty": 1,
      "question": "What does \"공부하다\" mean?",
      "answer": "to study",
      "translation": "to study",
      "options": [
        "to study",
        "sorry",
        "hello",
        "thank you"
      ],
      "pronunciation": "gongbuhada"
    },
    {
      "id": "ko-031-086",
      "word": "안녕하세요",
      "romanization": "annyeonghaseyo",
      "english": "hello",
      "type": "vocabulary",
      "difficulty": 1,
      "question": "What does \"안녕하세요\" mean?",
      "answer": "hello",
      "translation": "hello",
      "options": [
        "hello",
        "goodbye",
        "sorry",
        "thank you"
      ],
      "pronunciation": "annyeonghaseyo"
    },
    {
      "id": "ko-031-087",
      "word": "감사합니다",
      "romanization": "gamsahamnida",
      "english": "thank you",
      "type": "vocabulary",
      "difficulty": 1,
      "question": "What does \"감사합니다\" mean?",
      "answer": "thank you",
      "translation": "thank you",
      "options": [
        "hello",
        "goodbye",
        "thank you",
        "sorry"
      ],
      "pronunciation": "gamsahamnida"
    },
    {
      "id": "ko-031-088",
      "word": "죄송합니다",
      "romanization": "joesonghamnida",
      "english": "sorry",
      "type": "vocabulary",
      "difficulty": 1,
      "question": "What does \"죄송합니다\" mean?",
      "answer": "sorry",
      "translation": "sorry",
      "options": [
        "goodbye",
        "sorry",
        "thank you",
        "hello"
      ],
      "pronunciation": "joesonghamnida"
    },
    {
      "id": "ko-031-089",
      "word": "안녕히 가세요",
      "romanization": "annyeonghi gaseyo",
      "english": "goodbye",
      "type": "vocabulary",
      "difficulty": 1,
      "question": "What does \"안녕히 가세요\" mean?",
      "answer": "goodbye",
      "translation": "goodbye",
      "options": [
        "thank you",
        "hello",
        "sorry",
        "goodbye"
      ],
      "pronunciation": "annyeonghi gaseyo"
    },
    {
      "id": "ko-031-090",
      "word": "공부하다",
      "romanization": "gongbuhada",
      "english": "to study",
      "type": "vocabulary",
      "difficulty": 1,
      "question": "What does \"공부하다\" mean?",
      "answer": "to study",
      "translation": "to study",
      "options": [
        "to study",
        "sorry",
        "thank you",
        "hello"
      ],
      "pronunciation": "gongbuhada"
    },
    {
      "id": "ko-031-091",
      "word": "안녕하세요",
      "romanization": "annyeonghaseyo",
      "english": "hello",
      "type": "vocabulary",
      "difficulty": 1,
      "question": "What does \"안녕하세요\" mean?",
      "answer": "hello",
      "translation": "hello",
      "options": [
        "hello",
        "thank you",
        "sorry",
        "goodbye"
      ],
      "pronunciation": "annyeonghaseyo"
    },
    {
      "id": "ko-031-092",
      "word": "감사합니다",
      "romanization": "gamsahamnida",
      "english": "thank you",
      "type": "vocabulary",
      "difficulty": 1,
      "question": "What does \"감사합니다\" mean?",
      "answer": "thank you",
      "translation": "thank you",
      "options": [
        "thank you",
        "goodbye",
        "hello",
        "sorry"
      ],
      "pronunciation": "gamsahamnida"
    },
    {
      "id": "ko-031-093",
      "word": "죄송합니다",
      "romanization": "joesonghamnida",
      "english": "sorry",
      "type": "vocabulary",
      "difficulty": 1,
      "question": "What does \"죄송합니다\" mean?",
      "answer": "sorry",
      "translation": "sorry",
      "options": [
        "hello",
        "goodbye",
        "sorry",
        "thank you"
      ],
      "pronunciation": "joesonghamnida"
    },
    {
      "id": "ko-031-094",
      "word": "안녕히 가세요",
      "romanization": "annyeonghi gaseyo",
      "english": "goodbye",
      "type": "vocabulary",
      "difficulty": 1,
      "question": "What does \"안녕히 가세요\" mean?",
      "answer": "goodbye",
      "translation": "goodbye",
      "options": [
        "thank you",
        "goodbye",
        "hello",
        "sorry"
      ],
      "pronunciation": "annyeonghi gaseyo"
    },
    {
      "id": "ko-031-095",
      "word": "공부하다",
      "romanization": "gongbuhada",
      "english": "to study",
      "type": "vocabulary",
      "difficulty": 1,
      "question": "What does \"공부하다\" mean?",
      "answer": "to study",
      "translation": "to study",
      "options": [
        "sorry",
        "thank you",
        "hello",
        "to study"
      ],
      "pronunciation": "gongbuhada"
    },
    {
      "id": "ko-031-096",
      "word": "안녕하세요",
      "romanization": "annyeonghaseyo",
      "english": "hello",
      "type": "vocabulary",
      "difficulty": 1,
      "question": "What does \"안녕하세요\" mean?",
      "answer": "hello",
      "translation": "hello",
      "options": [
        "sorry",
        "thank you",
        "hello",
        "goodbye"
      ],
      "pronunciation": "annyeonghaseyo"
    },
    {
      "id": "ko-031-097",
      "word": "감사합니다",
      "romanization": "gamsahamnida",
      "english": "thank you",
      "type": "vocabulary",
      "difficulty": 1,
      "question": "What does \"감사합니다\" mean?",
      "answer": "thank you",
      "translation": "thank you",
      "options": [
        "sorry",
        "hello",
        "thank you",
        "goodbye"
      ],
      "pronunciation": "gamsahamnida"
    },
    {
      "id": "ko-031-098",
      "word": "죄송합니다",
      "romanization": "joesonghamnida",
      "english": "sorry",
      "type": "vocabulary",
      "difficulty": 1,
      "question": "What does \"죄송합니다\" mean?",
      "answer": "sorry",
      "translation": "sorry",
      "options": [
        "thank you",
        "goodbye",
        "hello",
        "sorry"
      ],
      "pronunciation": "joesonghamnida"
    },
    {
      "id": "ko-031-099",
      "word": "안녕히 가세요",
      "romanization": "annyeonghi gaseyo",
      "english": "goodbye",
      "type": "vocabulary",
      "difficulty": 1,
      "question": "What does \"안녕히 가세요\" mean?",
      "answer": "goodbye",
      "translation": "goodbye",
      "options": [
        "sorry",
        "goodbye",
        "hello",
        "thank you"
      ],
      "pronunciation": "annyeonghi gaseyo"
    },
    {
      "id": "ko-031-100",
      "word": "공부하다",
      "romanization": "gongbuhada",
      "english": "to study",
      "type": "vocabulary",
      "difficulty": 1,
      "question": "What does \"공부하다\" mean?",
      "answer": "to study",
      "translation": "to study",
      "options": [
        "sorry",
        "hello",
        "thank you",
        "to study"
      ],
      "pronunciation": "gongbuhada"
    }
  ]
}